odoo/addons/beesdoo_shift_swap/README.rst
odoo/addons/beesdoo_shift_swap/__init__.py
odoo/addons/beesdoo_shift_swap/__manifest__.py
odoo/addons/beesdoo_shift_swap/data/cron.xml
odoo/addons/beesdoo_shift_swap/data/mail_template.xml
odoo/addons/beesdoo_shift_swap/data/system_parameter.xml
odoo/addons/beesdoo_shift_swap/demo/demo.xml
odoo/addons/beesdoo_shift_swap/i18n/beesdoo_shift_swap.pot
odoo/addons/beesdoo_shift_swap/i18n/fr_BE.po
odoo/addons/beesdoo_shift_swap/i18n/nl_BE.po
odoo/addons/beesdoo_shift_swap/migrations/12.0.1.0.4/post-migrate.py
odoo/addons/beesdoo_shift_swap/models/__init__.py
odoo/addons/beesdoo_shift_swap/models/dated_template.py
odoo/addons/beesdoo_shift_swap/models/exchange.py
odoo/addons/beesdoo_shift_swap/models/exchange_request.py
odoo/addons/beesdoo_shift_swap/models/planning.py
odoo/addons/beesdoo_shift_swap/models/res_company.py
odoo/addons/beesdoo_shift_swap/models/res_config_settings.py
odoo/addons/beesdoo_shift_swap/models/res_partner.py
odoo/addons/beesdoo_shift_swap/models/shift_swap.py
odoo/addons/beesdoo_shift_swap/models/shift_swap_mixin.py
odoo/addons/beesdoo_shift_swap/models/solidarity_shift_offer.py
odoo/addons/beesdoo_shift_swap/models/solidarity_shift_request.py
odoo/addons/beesdoo_shift_swap/models/task.py
odoo/addons/beesdoo_shift_swap/readme/CONTRIBUTORS.rst
odoo/addons/beesdoo_shift_swap/readme/DESCRIPTION.rst
odoo/addons/beesdoo_shift_swap/security/ir.model.access.csv
odoo/addons/beesdoo_shift_swap/static/description/index.html
odoo/addons/beesdoo_shift_swap/tests/__init__.py
odoo/addons/beesdoo_shift_swap/tests/test_beesdoo_shift_swap.py
odoo/addons/beesdoo_shift_swap/views/res_config_setting_view.xml
odoo/addons/beesdoo_shift_swap/views/res_partner.xml
odoo/addons/beesdoo_shift_swap/views/shift_swap.xml
odoo/addons/beesdoo_shift_swap/views/shift_swap_proposale.xml
odoo/addons/beesdoo_shift_swap/views/shift_swap_set.xml
odoo/addons/beesdoo_shift_swap/views/shift_swap_subscribe.xml
odoo12_addon_beesdoo_shift_swap-12.0.2.1.0.dist-info/METADATA
odoo12_addon_beesdoo_shift_swap-12.0.2.1.0.dist-info/WHEEL
odoo12_addon_beesdoo_shift_swap-12.0.2.1.0.dist-info/top_level.txt
odoo12_addon_beesdoo_shift_swap-12.0.2.1.0.dist-info/RECORD
