Metadata-Version: 2.1
Name: odoo12-addon-beesdoo-shift-swap
Version: 12.0.2.1.0
Summary: Module to allow cooperator to swap his/her shift when he/she can't attend it, to do solidarity shifts, and to request solidarity if needed.
Home-page: https://github.com/beescoop/Obeesdoo
Author: Coop IT Easy SC
License: AGPL-3
Platform: UNKNOWN
Classifier: Programming Language :: Python
Classifier: Framework :: Odoo
Classifier: Framework :: Odoo :: 12.0
Classifier: License :: OSI Approved :: GNU Affero General Public License v3
Requires-Python: >=3.5
Requires-Dist: odoo12-addon-beesdoo-shift
Requires-Dist: odoo (<12.1dev,>=12.0a)
